setup.py
src/IntegraPy/__init__.py
src/IntegraPy/constants.py
src/IntegraPy/demo.py
src/IntegraPy/framing.py
src/IntegraPy.egg-info/PKG-INFO
src/IntegraPy.egg-info/SOURCES.txt
src/IntegraPy.egg-info/dependency_links.txt
src/IntegraPy.egg-info/not-zip-safe
src/IntegraPy.egg-info/requires.txt
src/IntegraPy.egg-info/top_level.txt