Metadata-Version: 1.0
Name: IntegraPy
Version: 1.0.1
Summary: Satel's Integra secrity hub interface
Home-page: UNKNOWN
Author: Marcin Korzonek & Michał Węgrzynek & al.
Author-email: UNKNOWN
License: GNU General Public License
Platform: UNKNOWN
